crypto_qr_codes/__init__.py
crypto_qr_codes/qr.py
crypto_qr_codes-0.1.8.dist-info/LICENSE
crypto_qr_codes-0.1.8.dist-info/METADATA
crypto_qr_codes-0.1.8.dist-info/WHEEL
crypto_qr_codes-0.1.8.dist-info/top_level.txt
crypto_qr_codes-0.1.8.dist-info/RECORD
