Metadata-Version: 2.1
Name: crypto-qr-codes
Version: 0.1.8
Summary: A package for generating QR codes for various cryptocurrencies
Home-page: https://github.com/RandoS-svk/CryptoQRGenerator
Author: Robert Capla
Author-email: robert.capla@icloud.com
Classifier: Programming Language :: Python :: 3
Classifier: License :: OSI Approved :: MIT License
Classifier: Operating System :: OS Independent
Requires-Python: >=3.6
License-File: LICENSE
Requires-Dist: qrcode
